<?xml version="1.0"?>
<!DOCTYPE hibernate-mapping PUBLIC
        "-//hibernate/hibernate Mapping DTD 3.0//EN"
        "file:./hibernate-mapping-3.0.dtd">

<hibernate-mapping>

	<class name="com.coreweb.domain.Operacion" table="UsuarioOperacion">
		<id name="id" column="id" type="long">
			<generator class="increment"/>
		</id>
		<property name="dbEstado" />
		<property name="alias"/>
		<property name="nombre"/>
		<property name="descripcion"/>
		<property name="habilitado"/>
		<property name="idTexto"/>
		<many-to-one name="formulario" class="com.coreweb.domain.Formulario"
			column="idFormulario"
			lazy="false" cascade="none" not-null="false" />


	</class>

</hibernate-mapping>
